genopyc/__init__.py
genopyc/__version__.py
genopyc/data/HUMAN_9606_idmapping.dat.gz
genopyc/data/Homo_sapiens.gene_info.gz
genopyc/data/__init__.py
genopyc/data/hippie_interactome.sif
genopyc/data/uberon_dict.pickle
genopyc/epidemiology/__init__.py
genopyc/epidemiology/get_associations.py
genopyc/epidemiology/get_gdas.py
genopyc/epidemiology/get_phenotypes.py
genopyc/epidemiology/get_summary_statistic.py
genopyc/epidemiology/get_summary_statistic_list.py
genopyc/epidemiology/locus_to_gene.py
genopyc/epidemiology/variant_effect_predictor.py
genopyc/eqtl/__init__.py
genopyc/eqtl/get_eqtl_df.py
genopyc/eqtl/make_eqtl_network.py
genopyc/genomic_features/__init__.py
genopyc/genomic_features/get_ancestral_allele.py
genopyc/genomic_features/get_closest_genes.py
genopyc/genomic_features/get_genes.py
genopyc/genomic_features/get_genes_position.py
genopyc/genomic_features/get_ov_region.py
genopyc/genomic_features/get_sequence.py
genopyc/genomic_features/get_variants_info.py
genopyc/genomic_features/get_variants_position.py
genopyc/linkage_disequilibrium/__init__.py
genopyc/linkage_disequilibrium/get_ld_matrix.py
genopyc/linkage_disequilibrium/get_variants_in_LD.py
genopyc/linkage_disequilibrium/pairwise_ld.py
genopyc/mapping/__init__.py
genopyc/mapping/geneId_mapping.py
genopyc/mapping/grch_liftover.py
genopyc/mapping/variantId_mapping.py
genopyc/plotting/FuEnViz.py
genopyc/plotting/__init__.py
genopyc/plotting/plot_enrichment_analysis_network.py
genopyc/utils/__init__.py
genopyc/utils/update_mapping_datasets.py
genopyc-2.7.8.dist-info/licenses/LICENSE.txt
genopyc-2.7.8.dist-info/METADATA
genopyc-2.7.8.dist-info/WHEEL
genopyc-2.7.8.dist-info/top_level.txt
genopyc-2.7.8.dist-info/RECORD
