Metadata-Version: 2.4
Name: genopyc
Version: 2.7.8
Author: Francesco Gualdi
License: GPL
License-File: LICENSE.txt
Requires-Dist: requests
Requires-Dist: wget
Requires-Dist: pandas
Requires-Dist: numpy
Requires-Dist: sphinx
Requires-Dist: networkx
Requires-Dist: igraph
Requires-Dist: dash
Requires-Dist: dash_cytoscape
Requires-Dist: gprofiler_official
Dynamic: author
Dynamic: description
Dynamic: description-content-type
Dynamic: license
Dynamic: license-file
Dynamic: requires-dist
